{
  "platforms": [
    {
      "platformId": "k-31-visby-2009",
      "displayName": "K 31 Visby - 2009, Version 4",
      "domain": "surface",
      "platformClass": "FFL - Corvette",
      "nationality": "Sweden",
      "combatRadiusNm": 1.0
    },
    {
      "platformId": "f-219-sachsen-type-f124-2006",
      "displayName": "F 219 Sachsen [Type F124] - 2006",
      "domain": "surface",
      "platformClass": "FFG - Guided Missile Frigate",
      "nationality": "Germany",
      "combatRadiusNm": 1.0
    },
    {
      "platformId": "f-341-absalon-2020",
      "displayName": "F 341 Absalon - 2020, 2x",
      "domain": "surface",
      "platformClass": "FFG - Guided Missile Frigate",
      "nationality": "Denmark",
      "combatRadiusNm": 1.0
    },
    {
      "platformId": "mpk-steregushchiy-pr-20380-2018",
      "displayName": "MPK Steregushchiy [Pr.20380] - 2018",
      "domain": "surface",
      "platformClass": "FFG - Guided Missile Frigate",
      "nationality": "Russia",
      "combatRadiusNm": 1.0
    },
    {
      "platformId": "mrk-buyan-mod-pr-21631-buyan-m-2014",
      "displayName": "MRK Buyan Mod [Pr.21631 Buyan-M] - 2014",
      "domain": "surface",
      "platformClass": "PCFG - Fast Guided Missile Patrol Craft",
      "nationality": "Russia",
      "combatRadiusNm": 1.0
    },
    {
      "platformId": "jas-39c-gripen-2005",
      "displayName": "JAS 39C Gripen - 2005, Batch 3, MS18.5, Gun & AIM-9L Only",
      "domain": "air",
      "platformClass": "Aircraft - Multirole (Fighter/Attack)",
      "nationality": "Sweden",
      "combatRadiusNm": 1.0
    },
    {
      "platformId": "jas-39e-gripen-ng-2021",
      "displayName": "JAS 39E Gripen NG - 2021, 28x",
      "domain": "air",
      "platformClass": "Aircraft - Multirole (Fighter/Attack)",
      "nationality": "Sweden",
      "combatRadiusNm": 1.0
    },
    {
      "platformId": "f-16c-blk-52iq-falcon-2015",
      "displayName": "F-16C Blk 52IQ Falcon - 2015",
      "domain": "air",
      "platformClass": "Aircraft - Multirole (Fighter/Attack)",
      "nationality": "Iraq",
      "combatRadiusNm": 1.0
    },
    {
      "platformId": "jas-39a-gripen-1997",
      "displayName": "JAS 39A Gripen - 1997, Batch 1",
      "domain": "air",
      "platformClass": "Aircraft - Multirole (Fighter/Attack)",
      "nationality": "Sweden",
      "combatRadiusNm": 1.0
    },
    {
      "platformId": "jas-39b-gripen-1997",
      "displayName": "JAS 39B Gripen - 1997, Batch 1",
      "domain": "air",
      "platformClass": "Aircraft - Multirole (Fighter/Attack)",
      "nationality": "Sweden",
      "combatRadiusNm": 1.0
    },
    {
      "platformId": "a-19-gotland-1996",
      "displayName": "A 19 Gotland - 1996",
      "domain": "subsurface",
      "platformClass": "SSK - Hunter-Killer Submarine",
      "nationality": "Sweden",
      "combatRadiusNm": 1.0
    },
    {
      "platformId": "a-19-gotland-2022",
      "displayName": "A 19 Gotland - 2022, Tp 47",
      "domain": "subsurface",
      "platformClass": "SSK - Hunter-Killer Submarine",
      "nationality": "Sweden",
      "combatRadiusNm": 1.0
    },
    {
      "platformId": "021-messali-el-hadj-pl-636m-kilo-2011",
      "displayName": "021 Messali el Hadj [PL-636M Kilo] - 2011",
      "domain": "subsurface",
      "platformClass": "SS - Attack/Fleet Submarine",
      "nationality": "Algeria",
      "combatRadiusNm": 1.0
    },
    {
      "platformId": "a-17-vastergotland-1999",
      "displayName": "A 17 Vastergotland - 1999",
      "domain": "subsurface",
      "platformClass": "SSK - Hunter-Killer Submarine",
      "nationality": "Sweden",
      "combatRadiusNm": 1.0
    },
    {
      "platformId": "hostile-1",
      "displayName": "",
      "domain": "surface",
      "platformClass": "",
      "nationality": "",
      "combatRadiusNm": 200.0
    },
    {
      "platformId": "hostile-far",
      "displayName": "",
      "domain": "surface",
      "platformClass": "",
      "nationality": "",
      "combatRadiusNm": 200.0
    },
    {
      "platformId": "u1",
      "displayName": "",
      "domain": "surface",
      "platformClass": "",
      "nationality": "",
      "combatRadiusNm": 400.0
    }
  ],
  "sensors": [
    {
      "platformId": "021-messali-el-hadj-pl-636m-kilo-2011",
      "sensorId": "cmo-sensor-1042",
      "basePd": 0.24666666666666667,
      "reviewState": "approved"
    },
    {
      "platformId": "021-messali-el-hadj-pl-636m-kilo-2011",
      "sensorId": "cmo-sensor-1676",
      "basePd": 0.24666666666666667,
      "reviewState": "approved"
    },
    {
      "platformId": "021-messali-el-hadj-pl-636m-kilo-2011",
      "sensorId": "cmo-sensor-2072",
      "basePd": 0.24666666666666667,
      "reviewState": "approved"
    },
    {
      "platformId": "021-messali-el-hadj-pl-636m-kilo-2011",
      "sensorId": "cmo-sensor-4176",
      "basePd": 0.24666666666666667,
      "reviewState": "approved"
    },
    {
      "platformId": "021-messali-el-hadj-pl-636m-kilo-2011",
      "sensorId": "cmo-sensor-4177",
      "basePd": 0.24666666666666667,
      "reviewState": "approved"
    },
    {
      "platformId": "021-messali-el-hadj-pl-636m-kilo-2011",
      "sensorId": "cmo-sensor-4539",
      "basePd": 0.24666666666666667,
      "reviewState": "approved"
    },
    {
      "platformId": "a-17-vastergotland-1999",
      "sensorId": "cmo-sensor-1344",
      "basePd": 0.24666666666666667,
      "reviewState": "approved"
    },
    {
      "platformId": "a-17-vastergotland-1999",
      "sensorId": "cmo-sensor-1741",
      "basePd": 0.24666666666666667,
      "reviewState": "approved"
    },
    {
      "platformId": "a-17-vastergotland-1999",
      "sensorId": "cmo-sensor-1807",
      "basePd": 0.24666666666666667,
      "reviewState": "approved"
    },
    {
      "platformId": "a-17-vastergotland-1999",
      "sensorId": "cmo-sensor-1910",
      "basePd": 0.24666666666666667,
      "reviewState": "approved"
    },
    {
      "platformId": "a-17-vastergotland-1999",
      "sensorId": "cmo-sensor-4407",
      "basePd": 0.24666666666666667,
      "reviewState": "approved"
    },
    {
      "platformId": "a-17-vastergotland-1999",
      "sensorId": "cmo-sensor-68",
      "basePd": 0.24666666666666667,
      "reviewState": "approved"
    },
    {
      "platformId": "a-19-gotland-1996",
      "sensorId": "cmo-sensor-2082",
      "basePd": 0.24666666666666667,
      "reviewState": "approved"
    },
    {
      "platformId": "a-19-gotland-1996",
      "sensorId": "cmo-sensor-2084",
      "basePd": 0.24666666666666667,
      "reviewState": "approved"
    },
    {
      "platformId": "a-19-gotland-1996",
      "sensorId": "cmo-sensor-2085",
      "basePd": 0.24666666666666667,
      "reviewState": "approved"
    },
    {
      "platformId": "a-19-gotland-1996",
      "sensorId": "cmo-sensor-4216",
      "basePd": 0.24666666666666667,
      "reviewState": "approved"
    },
    {
      "platformId": "a-19-gotland-1996",
      "sensorId": "cmo-sensor-4410",
      "basePd": 0.24666666666666667,
      "reviewState": "approved"
    },
    {
      "platformId": "a-19-gotland-1996",
      "sensorId": "cmo-sensor-4678",
      "basePd": 0.24666666666666667,
      "reviewState": "approved"
    },
    {
      "platformId": "a-19-gotland-2022",
      "sensorId": "cmo-sensor-2084",
      "basePd": 0.15433333333333332,
      "reviewState": "approved"
    },
    {
      "platformId": "a-19-gotland-2022",
      "sensorId": "cmo-sensor-2085",
      "basePd": 0.148,
      "reviewState": "approved"
    },
    {
      "platformId": "a-19-gotland-2022",
      "sensorId": "cmo-sensor-2582",
      "basePd": 1.0,
      "reviewState": "approved"
    },
    {
      "platformId": "a-19-gotland-2022",
      "sensorId": "cmo-sensor-4216",
      "basePd": 0.24699999999999997,
      "reviewState": "approved"
    },
    {
      "platformId": "a-19-gotland-2022",
      "sensorId": "cmo-sensor-4410",
      "basePd": 0.426,
      "reviewState": "approved"
    },
    {
      "platformId": "a-19-gotland-2022",
      "sensorId": "cmo-sensor-5865",
      "basePd": 0.139,
      "reviewState": "approved"
    },
    {
      "platformId": "a-19-gotland-2022",
      "sensorId": "cmo-sensor-5866",
      "basePd": 0.139,
      "reviewState": "approved"
    },
    {
      "platformId": "a-19-gotland-2022",
      "sensorId": "cmo-sensor-6606",
      "basePd": 0.05,
      "reviewState": "approved"
    },
    {
      "platformId": "f-16c-blk-52iq-falcon-2015",
      "sensorId": "cmo-sensor-1438",
      "basePd": 0.49399999999999994,
      "reviewState": "approved"
    },
    {
      "platformId": "f-16c-blk-52iq-falcon-2015",
      "sensorId": "cmo-sensor-1920",
      "basePd": 0.05,
      "reviewState": "approved"
    },
    {
      "platformId": "f-16c-blk-52iq-falcon-2015",
      "sensorId": "cmo-sensor-4397",
      "basePd": 0.7406666666666666,
      "reviewState": "approved"
    },
    {
      "platformId": "f-219-sachsen-type-f124-2006",
      "sensorId": "cmo-sensor-1829",
      "basePd": 1.0,
      "reviewState": "approved"
    },
    {
      "platformId": "f-219-sachsen-type-f124-2006",
      "sensorId": "cmo-sensor-1830",
      "basePd": 0.05,
      "reviewState": "approved"
    },
    {
      "platformId": "f-219-sachsen-type-f124-2006",
      "sensorId": "cmo-sensor-2009",
      "basePd": 0.5556666666666666,
      "reviewState": "approved"
    },
    {
      "platformId": "f-219-sachsen-type-f124-2006",
      "sensorId": "cmo-sensor-2010",
      "basePd": 1.0,
      "reviewState": "approved"
    },
    {
      "platformId": "f-219-sachsen-type-f124-2006",
      "sensorId": "cmo-sensor-2012",
      "basePd": 0.24699999999999997,
      "reviewState": "approved"
    },
    {
      "platformId": "f-219-sachsen-type-f124-2006",
      "sensorId": "cmo-sensor-203",
      "basePd": 0.15433333333333332,
      "reviewState": "approved"
    },
    {
      "platformId": "f-219-sachsen-type-f124-2006",
      "sensorId": "cmo-sensor-353",
      "basePd": 0.148,
      "reviewState": "approved"
    },
    {
      "platformId": "f-219-sachsen-type-f124-2006",
      "sensorId": "cmo-sensor-519",
      "basePd": 1.0,
      "reviewState": "approved"
    },
    {
      "platformId": "f-341-absalon-2020",
      "sensorId": "cmo-sensor-2234",
      "basePd": 0.24666666666666667,
      "reviewState": "approved"
    },
    {
      "platformId": "f-341-absalon-2020",
      "sensorId": "cmo-sensor-2238",
      "basePd": 0.24666666666666667,
      "reviewState": "approved"
    },
    {
      "platformId": "f-341-absalon-2020",
      "sensorId": "cmo-sensor-2556",
      "basePd": 0.24666666666666667,
      "reviewState": "approved"
    },
    {
      "platformId": "f-341-absalon-2020",
      "sensorId": "cmo-sensor-2582",
      "basePd": 0.24666666666666667,
      "reviewState": "approved"
    },
    {
      "platformId": "f-341-absalon-2020",
      "sensorId": "cmo-sensor-3354",
      "basePd": 0.24666666666666667,
      "reviewState": "approved"
    },
    {
      "platformId": "f-341-absalon-2020",
      "sensorId": "cmo-sensor-5652",
      "basePd": 0.24666666666666667,
      "reviewState": "approved"
    },
    {
      "platformId": "jas-39a-gripen-1997",
      "sensorId": "cmo-sensor-1331",
      "basePd": 0.24666666666666667,
      "reviewState": "approved"
    },
    {
      "platformId": "jas-39a-gripen-1997",
      "sensorId": "cmo-sensor-664",
      "basePd": 0.24666666666666667,
      "reviewState": "approved"
    },
    {
      "platformId": "jas-39a-gripen-1997",
      "sensorId": "cmo-sensor-825",
      "basePd": 0.24666666666666667,
      "reviewState": "approved"
    },
    {
      "platformId": "jas-39b-gripen-1997",
      "sensorId": "cmo-sensor-1331",
      "basePd": 0.24666666666666667,
      "reviewState": "approved"
    },
    {
      "platformId": "jas-39b-gripen-1997",
      "sensorId": "cmo-sensor-664",
      "basePd": 0.24666666666666667,
      "reviewState": "approved"
    },
    {
      "platformId": "jas-39b-gripen-1997",
      "sensorId": "cmo-sensor-825",
      "basePd": 0.24666666666666667,
      "reviewState": "approved"
    },
    {
      "platformId": "jas-39c-gripen-2005",
      "sensorId": "cmo-sensor-1315",
      "basePd": 0.7406666666666666,
      "reviewState": "approved"
    },
    {
      "platformId": "jas-39c-gripen-2005",
      "sensorId": "cmo-sensor-664",
      "basePd": 0.7406666666666666,
      "reviewState": "approved"
    },
    {
      "platformId": "jas-39e-gripen-ng-2021",
      "sensorId": "cmo-sensor-1315",
      "basePd": 0.7406666666666666,
      "reviewState": "approved"
    },
    {
      "platformId": "jas-39e-gripen-ng-2021",
      "sensorId": "cmo-sensor-5074",
      "basePd": 0.7406666666666666,
      "reviewState": "approved"
    },
    {
      "platformId": "jas-39e-gripen-ng-2021",
      "sensorId": "cmo-sensor-5236",
      "basePd": 0.6173333333333333,
      "reviewState": "approved"
    },
    {
      "platformId": "jas-39e-gripen-ng-2021",
      "sensorId": "cmo-sensor-825",
      "basePd": 0.05,
      "reviewState": "approved"
    },
    {
      "platformId": "k-31-visby-2009",
      "sensorId": "cmo-sensor-1827",
      "basePd": 0.09266666666666667,
      "reviewState": "approved"
    },
    {
      "platformId": "k-31-visby-2009",
      "sensorId": "cmo-sensor-2419",
      "basePd": 0.09266666666666667,
      "reviewState": "approved"
    },
    {
      "platformId": "k-31-visby-2009",
      "sensorId": "cmo-sensor-2556",
      "basePd": 0.6173333333333333,
      "reviewState": "approved"
    },
    {
      "platformId": "k-31-visby-2009",
      "sensorId": "cmo-sensor-2582",
      "basePd": 1.0,
      "reviewState": "approved"
    },
    {
      "platformId": "k-31-visby-2009",
      "sensorId": "cmo-sensor-2776",
      "basePd": 0.6,
      "reviewState": "approved"
    },
    {
      "platformId": "k-31-visby-2009",
      "sensorId": "cmo-sensor-3354",
      "basePd": 0.6173333333333333,
      "reviewState": "approved"
    },
    {
      "platformId": "k-31-visby-2009",
      "sensorId": "cmo-sensor-567",
      "basePd": 0.05,
      "reviewState": "approved"
    },
    {
      "platformId": "k-31-visby-2009",
      "sensorId": "cmo-sensor-568",
      "basePd": 0.29633333333333334,
      "reviewState": "approved"
    },
    {
      "platformId": "mpk-steregushchiy-pr-20380-2018",
      "sensorId": "cmo-sensor-369",
      "basePd": 0.6173333333333333,
      "reviewState": "approved"
    },
    {
      "platformId": "mpk-steregushchiy-pr-20380-2018",
      "sensorId": "cmo-sensor-4231",
      "basePd": 0.05,
      "reviewState": "approved"
    },
    {
      "platformId": "mpk-steregushchiy-pr-20380-2018",
      "sensorId": "cmo-sensor-4961",
      "basePd": 0.432,
      "reviewState": "approved"
    },
    {
      "platformId": "mpk-steregushchiy-pr-20380-2018",
      "sensorId": "cmo-sensor-4963",
      "basePd": 0.29633333333333334,
      "reviewState": "approved"
    },
    {
      "platformId": "mpk-steregushchiy-pr-20380-2018",
      "sensorId": "cmo-sensor-4965",
      "basePd": 0.24699999999999997,
      "reviewState": "approved"
    },
    {
      "platformId": "mpk-steregushchiy-pr-20380-2018",
      "sensorId": "cmo-sensor-4966",
      "basePd": 0.05,
      "reviewState": "approved"
    },
    {
      "platformId": "mpk-steregushchiy-pr-20380-2018",
      "sensorId": "cmo-sensor-504",
      "basePd": 0.6173333333333333,
      "reviewState": "approved"
    },
    {
      "platformId": "mpk-steregushchiy-pr-20380-2018",
      "sensorId": "cmo-sensor-5612",
      "basePd": 0.05,
      "reviewState": "approved"
    },
    {
      "platformId": "mrk-buyan-mod-pr-21631-buyan-m-2014",
      "sensorId": "cmo-sensor-115",
      "basePd": 0.432,
      "reviewState": "approved"
    },
    {
      "platformId": "mrk-buyan-mod-pr-21631-buyan-m-2014",
      "sensorId": "cmo-sensor-1579",
      "basePd": 0.15433333333333332,
      "reviewState": "approved"
    },
    {
      "platformId": "mrk-buyan-mod-pr-21631-buyan-m-2014",
      "sensorId": "cmo-sensor-1581",
      "basePd": 0.15433333333333332,
      "reviewState": "approved"
    },
    {
      "platformId": "mrk-buyan-mod-pr-21631-buyan-m-2014",
      "sensorId": "cmo-sensor-3410",
      "basePd": 0.074,
      "reviewState": "approved"
    },
    {
      "platformId": "mrk-buyan-mod-pr-21631-buyan-m-2014",
      "sensorId": "cmo-sensor-3591",
      "basePd": 0.05,
      "reviewState": "approved"
    },
    {
      "platformId": "mrk-buyan-mod-pr-21631-buyan-m-2014",
      "sensorId": "cmo-sensor-3663",
      "basePd": 0.24699999999999997,
      "reviewState": "approved"
    },
    {
      "platformId": "mrk-buyan-mod-pr-21631-buyan-m-2014",
      "sensorId": "cmo-sensor-5611",
      "basePd": 1.0,
      "reviewState": "approved"
    },
    {
      "platformId": "mrk-buyan-mod-pr-21631-buyan-m-2014",
      "sensorId": "cmo-sensor-5612",
      "basePd": 0.05,
      "reviewState": "approved"
    },
    {
      "platformId": "u1",
      "sensorId": "radar-1",
      "basePd": 1.0,
      "reviewState": "approved"
    },
    {
      "platformId": "u1",
      "sensorId": "radar-2",
      "basePd": 0.75,
      "reviewState": "approved"
    }
  ],
  "weapons": [
    {
      "weaponId": "cmo-weapon-1000",
      "displayName": "RIM-116B RAM Blk I",
      "minRangeMeters": 0.0,
      "maxRangeMeters": 11100.0
    },
    {
      "weaponId": "cmo-weapon-1019",
      "displayName": "M/70 135mm Rocket",
      "minRangeMeters": 0.0,
      "maxRangeMeters": 3700.0
    },
    {
      "weaponId": "cmo-weapon-1020",
      "displayName": "RB 75 Maverick EO [AGM-65B]",
      "minRangeMeters": 0.0,
      "maxRangeMeters": 11100.0
    },
    {
      "weaponId": "cmo-weapon-1021",
      "displayName": "RB 74 Sidewinder [AIM-9L]",
      "minRangeMeters": 0.0,
      "maxRangeMeters": 18500.0
    },
    {
      "weaponId": "cmo-weapon-1068",
      "displayName": "AN/SLQ-25 Nixie",
      "minRangeMeters": 0.0,
      "maxRangeMeters": 1900.0
    },
    {
      "weaponId": "cmo-weapon-1071",
      "displayName": "BK 90 Mjolner Mk2 [24 x MJ2 Anti-Tank]",
      "minRangeMeters": 0.0,
      "maxRangeMeters": 14800.0
    },
    {
      "weaponId": "cmo-weapon-1072",
      "displayName": "BK 90 Mjolner Mk1 [72 x MJ1 Anti-Personnel]",
      "minRangeMeters": 0.0,
      "maxRangeMeters": 14800.0
    },
    {
      "weaponId": "cmo-weapon-1094",
      "displayName": "TEST-96",
      "minRangeMeters": 0.0,
      "maxRangeMeters": 7400.0
    },
    {
      "weaponId": "cmo-weapon-1108",
      "displayName": "AK-630M 30mm/65 Gatling Burst [400 rnds]",
      "minRangeMeters": 0.0,
      "maxRangeMeters": 1900.0
    },
    {
      "weaponId": "cmo-weapon-1110",
      "displayName": "14.5mm MG Burst [20 rnds]",
      "minRangeMeters": 0.0,
      "maxRangeMeters": 1900.0
    },
    {
      "weaponId": "cmo-weapon-1119",
      "displayName": "53-65KE WH",
      "minRangeMeters": 0.0,
      "maxRangeMeters": 7400.0
    },
    {
      "weaponId": "cmo-weapon-1128",
      "displayName": "RB 98 [AIM-2000A] IRIS-T",
      "minRangeMeters": 0.0,
      "maxRangeMeters": 27800.0
    },
    {
      "weaponId": "cmo-weapon-1140",
      "displayName": "57mm/70 Bofors Mk3 GP Burst [4 rnds]",
      "minRangeMeters": 0.0,
      "maxRangeMeters": 2200.0
    },
    {
      "weaponId": "cmo-weapon-1195",
      "displayName": "RIM-66M-2 SM-2MR Blk IIIA",
      "minRangeMeters": 0.0,
      "maxRangeMeters": 166700.0
    },
    {
      "weaponId": "cmo-weapon-1227",
      "displayName": "PK-10 Flare [SO-50]",
      "minRangeMeters": 0.0,
      "maxRangeMeters": 1900.0
    },
    {
      "weaponId": "cmo-weapon-1228",
      "displayName": "PK-10 Chaff [SR-50]",
      "minRangeMeters": 0.0,
      "maxRangeMeters": 1900.0
    },
    {
      "weaponId": "cmo-weapon-1273",
      "displayName": "Bullfighter Chaff/Flare Seduction",
      "minRangeMeters": 0.0,
      "maxRangeMeters": 1900.0
    },
    {
      "weaponId": "cmo-weapon-1274",
      "displayName": "Chimera Chaff/Flare Seduction Round",
      "minRangeMeters": 0.0,
      "maxRangeMeters": 1900.0
    },
    {
      "weaponId": "cmo-weapon-1291",
      "displayName": "SPK-39 Pod [EO]",
      "minRangeMeters": 0.0,
      "maxRangeMeters": 40000.0
    },
    {
      "weaponId": "cmo-weapon-1292",
      "displayName": "Litening III Pod [FLIR + LRMTS, 40k ft]",
      "minRangeMeters": 0.0,
      "maxRangeMeters": 40000.0
    },
    {
      "weaponId": "cmo-weapon-1374",
      "displayName": "AK-176 76mm/60 Frag Burst [2 rnds]",
      "minRangeMeters": 0.0,
      "maxRangeMeters": 2800.0
    },
    {
      "weaponId": "cmo-weapon-1384",
      "displayName": "AIM-9M Sidewinder",
      "minRangeMeters": 0.0,
      "maxRangeMeters": 18500.0
    },
    {
      "weaponId": "cmo-weapon-1394",
      "displayName": "127mm/62 HE-CVT [HiFrag]",
      "minRangeMeters": 0.0,
      "maxRangeMeters": 2800.0
    },
    {
      "weaponId": "cmo-weapon-1400",
      "displayName": "AIM-7M Sparrow III",
      "minRangeMeters": 0.0,
      "maxRangeMeters": 70400.0
    },
    {
      "weaponId": "cmo-weapon-1401",
      "displayName": "AIM-9L Sidewinder",
      "minRangeMeters": 0.0,
      "maxRangeMeters": 18500.0
    },
    {
      "weaponId": "cmo-weapon-1402",
      "displayName": "Tp 431",
      "minRangeMeters": 0.0,
      "maxRangeMeters": 7400.0
    },
    {
      "weaponId": "cmo-weapon-1403",
      "displayName": "Tp 613",
      "minRangeMeters": 0.0,
      "maxRangeMeters": 9300.0
    },
    {
      "weaponId": "cmo-weapon-1450",
      "displayName": "MU-90 Impact",
      "minRangeMeters": 0.0,
      "maxRangeMeters": 7400.0
    },
    {
      "weaponId": "cmo-weapon-1523",
      "displayName": "300 USG Drop Tank",
      "minRangeMeters": 0.0,
      "maxRangeMeters": 40000.0
    },
    {
      "weaponId": "cmo-weapon-1536",
      "displayName": "1200 liter Drop Tank",
      "minRangeMeters": 0.0,
      "maxRangeMeters": 40000.0
    },
    {
      "weaponId": "cmo-weapon-1595",
      "displayName": "Tp 45",
      "minRangeMeters": 0.0,
      "maxRangeMeters": 7400.0
    },
    {
      "weaponId": "cmo-weapon-1611",
      "displayName": "RGM-84D Harpoon IC",
      "minRangeMeters": 0.0,
      "maxRangeMeters": 138900.0
    },
    {
      "weaponId": "cmo-weapon-166",
      "displayName": "76mm/62 Super Rapido HE Burst [2 rnds]",
      "minRangeMeters": 0.0,
      "maxRangeMeters": 2800.0
    },
    {
      "weaponId": "cmo-weapon-1695",
      "displayName": "12.7mm/50 MG Burst [10 rnds]",
      "minRangeMeters": 0.0,
      "maxRangeMeters": 1900.0
    },
    {
      "weaponId": "cmo-weapon-1763",
      "displayName": "370 USG Drop Tank",
      "minRangeMeters": 0.0,
      "maxRangeMeters": 40000.0
    },
    {
      "weaponId": "cmo-weapon-1814",
      "displayName": "Mk82 500lb LDGP",
      "minRangeMeters": 0.0,
      "maxRangeMeters": 1900.0
    },
    {
      "weaponId": "cmo-weapon-1839",
      "displayName": "Mk84 2000lb LDGP",
      "minRangeMeters": 0.0,
      "maxRangeMeters": 1900.0
    },
    {
      "weaponId": "cmo-weapon-1906",
      "displayName": "GBU-12D/B Paveway II LGB [Mk82]",
      "minRangeMeters": 0.0,
      "maxRangeMeters": 7400.0
    },
    {
      "weaponId": "cmo-weapon-1920",
      "displayName": "GBU-10E/B Paveway II LGB [Mk84]",
      "minRangeMeters": 0.0,
      "maxRangeMeters": 7400.0
    },
    {
      "weaponId": "cmo-weapon-2023",
      "displayName": "35mm/79 Oerlikon Millennium GDM-008 AHEAD Burst [24 rnds]",
      "minRangeMeters": 0.0,
      "maxRangeMeters": 1900.0
    },
    {
      "weaponId": "cmo-weapon-21",
      "displayName": "1275 liter Drop Tank",
      "minRangeMeters": 0.0,
      "maxRangeMeters": 40000.0
    },
    {
      "weaponId": "cmo-weapon-2182",
      "displayName": "SA-N-11b Grisom [9M311K-1]",
      "minRangeMeters": 0.0,
      "maxRangeMeters": 9300.0
    },
    {
      "weaponId": "cmo-weapon-2183",
      "displayName": "30mm Twin Gatling Gsh-6-30KD [375 rnds]",
      "minRangeMeters": 0.0,
      "maxRangeMeters": 1900.0
    },
    {
      "weaponId": "cmo-weapon-22",
      "displayName": "AGM-65K Maverick IR",
      "minRangeMeters": 0.0,
      "maxRangeMeters": 14800.0
    },
    {
      "weaponId": "cmo-weapon-2693",
      "displayName": "SA-N-24 Grinch [9M342]",
      "minRangeMeters": 0.0,
      "maxRangeMeters": 5600.0
    },
    {
      "weaponId": "cmo-weapon-2694",
      "displayName": "Paket-NK [MTT ASW]",
      "minRangeMeters": 0.0,
      "maxRangeMeters": 7400.0
    },
    {
      "weaponId": "cmo-weapon-2713",
      "displayName": "SS-N-30A Sagaris [3M14 Kalibr]",
      "minRangeMeters": 0.0,
      "maxRangeMeters": 1389000.0
    },
    {
      "weaponId": "cmo-weapon-282",
      "displayName": "RB 15F Mk2",
      "minRangeMeters": 0.0,
      "maxRangeMeters": 148200.0
    },
    {
      "weaponId": "cmo-weapon-290",
      "displayName": "RB 15F Mk1",
      "minRangeMeters": 0.0,
      "maxRangeMeters": 83300.0
    },
    {
      "weaponId": "cmo-weapon-2925",
      "displayName": "Generic Acoustic Decoy",
      "minRangeMeters": 0.0,
      "maxRangeMeters": 1900.0
    },
    {
      "weaponId": "cmo-weapon-3038",
      "displayName": "AK-630M 30mm/65 Twin Gatling Burst [800 rnds]",
      "minRangeMeters": 0.0,
      "maxRangeMeters": 1900.0
    },
    {
      "weaponId": "cmo-weapon-3153",
      "displayName": "Paket-NK [M-15 Anti-Torpedo Torpedo]",
      "minRangeMeters": 0.0,
      "maxRangeMeters": 1900.0
    },
    {
      "weaponId": "cmo-weapon-3218",
      "displayName": "SS-N-27 Sizzler [3M54T Kalibr]",
      "minRangeMeters": 0.0,
      "maxRangeMeters": 370400.0
    },
    {
      "weaponId": "cmo-weapon-371",
      "displayName": "RB 101 Meteor",
      "minRangeMeters": 0.0,
      "maxRangeMeters": 185200.0
    },
    {
      "weaponId": "cmo-weapon-3936",
      "displayName": "Tp 47",
      "minRangeMeters": 0.0,
      "maxRangeMeters": 20000.0
    },
    {
      "weaponId": "cmo-weapon-455",
      "displayName": "DUAL TRAP Chaff/Flare",
      "minRangeMeters": 0.0,
      "maxRangeMeters": 1900.0
    },
    {
      "weaponId": "cmo-weapon-459",
      "displayName": "AN/AAQ-33 Sniper XR Pod [FLIR + LRMTS, 40k ft]",
      "minRangeMeters": 0.0,
      "maxRangeMeters": 40000.0
    },
    {
      "weaponId": "cmo-weapon-494",
      "displayName": "100mm/59 A-190 HE",
      "minRangeMeters": 0.0,
      "maxRangeMeters": 14800.0
    },
    {
      "weaponId": "cmo-weapon-495",
      "displayName": "100mm/59 A-190 Frag",
      "minRangeMeters": 0.0,
      "maxRangeMeters": 2800.0
    },
    {
      "weaponId": "cmo-weapon-496",
      "displayName": "FIM-92E Stinger RMP Blk I",
      "minRangeMeters": 0.0,
      "maxRangeMeters": 5600.0
    },
    {
      "weaponId": "cmo-weapon-523",
      "displayName": "SA-N-8 Gremlin [9M36]",
      "minRangeMeters": 0.0,
      "maxRangeMeters": 5600.0
    },
    {
      "weaponId": "cmo-weapon-589",
      "displayName": "RGM-84L Harpoon II",
      "minRangeMeters": 0.0,
      "maxRangeMeters": 138900.0
    },
    {
      "weaponId": "cmo-weapon-596",
      "displayName": "127mm/62 HE-PD [HiCap]",
      "minRangeMeters": 0.0,
      "maxRangeMeters": 2800.0
    },
    {
      "weaponId": "cmo-weapon-597",
      "displayName": "127mm/62 WP",
      "minRangeMeters": 0.0,
      "maxRangeMeters": 22200.0
    },
    {
      "weaponId": "cmo-weapon-680",
      "displayName": "27mm MLG-27 Burst [20 rnds]",
      "minRangeMeters": 0.0,
      "maxRangeMeters": 1500.0
    },
    {
      "weaponId": "cmo-weapon-8",
      "displayName": "SS-N-27 Sizzler [3M54E1 Klub]",
      "minRangeMeters": 0.0,
      "maxRangeMeters": 220000.0
    },
    {
      "weaponId": "cmo-weapon-871",
      "displayName": "GBU-24A/B Paveway III LGB [BLU-109/B]",
      "minRangeMeters": 0.0,
      "maxRangeMeters": 14800.0
    },
    {
      "weaponId": "cmo-weapon-901",
      "displayName": "Tp 62",
      "minRangeMeters": 0.0,
      "maxRangeMeters": 11100.0
    },
    {
      "weaponId": "cmo-weapon-926",
      "displayName": "RIM-162C ESSM",
      "minRangeMeters": 0.0,
      "maxRangeMeters": 55600.0
    },
    {
      "weaponId": "cmo-weapon-927",
      "displayName": "RIM-162B ESSM",
      "minRangeMeters": 0.0,
      "maxRangeMeters": 55600.0
    },
    {
      "weaponId": "cmo-weapon-969",
      "displayName": "SS-N-25 Switchblade [Kh-35 Uran] GLONASS",
      "minRangeMeters": 0.0,
      "maxRangeMeters": 148200.0
    },
    {
      "weaponId": "cmo-weapon-1407",
      "displayName": "Elma ASW-600 ASW Mortar Salvo [M83 Soft Kill DC, 9 rnds]",
      "minRangeMeters": 0.0,
      "maxRangeMeters": 400.0
    },
    {
      "weaponId": "cmo-weapon-1495",
      "displayName": "57mm/70 Bofors Mk2 GP Burst [4 rnds]",
      "minRangeMeters": 0.0,
      "maxRangeMeters": 2200.0
    },
    {
      "weaponId": "cmo-weapon-1653",
      "displayName": "40mm/70 Single Bofors Burst [4 rnds]",
      "minRangeMeters": 0.0,
      "maxRangeMeters": 2200.0
    },
    {
      "weaponId": "cmo-weapon-1817",
      "displayName": "Philax Flare",
      "minRangeMeters": 0.0,
      "maxRangeMeters": 1900.0
    },
    {
      "weaponId": "cmo-weapon-1818",
      "displayName": "Philax Chaff",
      "minRangeMeters": 0.0,
      "maxRangeMeters": 1900.0
    }
  ],
  "magazines": [
    {
      "platformId": "021-messali-el-hadj-pl-636m-kilo-2011",
      "loadoutId": "default",
      "mountId": "53-65ke-wh",
      "weaponId": "cmo-weapon-1119",
      "quantity": 16
    },
    {
      "platformId": "021-messali-el-hadj-pl-636m-kilo-2011",
      "loadoutId": "default",
      "mountId": "generic-acoustic-decoy",
      "weaponId": "cmo-weapon-2925",
      "quantity": 16
    },
    {
      "platformId": "021-messali-el-hadj-pl-636m-kilo-2011",
      "loadoutId": "default",
      "mountId": "sa-n-8-gremlin-9m36",
      "weaponId": "cmo-weapon-523",
      "quantity": 16
    },
    {
      "platformId": "021-messali-el-hadj-pl-636m-kilo-2011",
      "loadoutId": "default",
      "mountId": "ss-n-27-sizzler-3m54e1-klub",
      "weaponId": "cmo-weapon-8",
      "quantity": 16
    },
    {
      "platformId": "021-messali-el-hadj-pl-636m-kilo-2011",
      "loadoutId": "default",
      "mountId": "test-96",
      "weaponId": "cmo-weapon-1094",
      "quantity": 16
    },
    {
      "platformId": "a-17-vastergotland-1999",
      "loadoutId": "default",
      "mountId": "generic-acoustic-decoy",
      "weaponId": "cmo-weapon-2925",
      "quantity": 16
    },
    {
      "platformId": "a-17-vastergotland-1999",
      "loadoutId": "default",
      "mountId": "tp-45",
      "weaponId": "cmo-weapon-1595",
      "quantity": 16
    },
    {
      "platformId": "a-17-vastergotland-1999",
      "loadoutId": "default",
      "mountId": "tp-613",
      "weaponId": "cmo-weapon-1403",
      "quantity": 16
    },
    {
      "platformId": "a-19-gotland-1996",
      "loadoutId": "default",
      "mountId": "generic-acoustic-decoy",
      "weaponId": "cmo-weapon-2925",
      "quantity": 16
    },
    {
      "platformId": "a-19-gotland-1996",
      "loadoutId": "default",
      "mountId": "tp-431",
      "weaponId": "cmo-weapon-1402",
      "quantity": 16
    },
    {
      "platformId": "a-19-gotland-1996",
      "loadoutId": "default",
      "mountId": "tp-613",
      "weaponId": "cmo-weapon-1403",
      "quantity": 16
    },
    {
      "platformId": "a-19-gotland-2022",
      "loadoutId": "default",
      "mountId": "generic-acoustic-decoy",
      "weaponId": "cmo-weapon-2925",
      "quantity": 16
    },
    {
      "platformId": "a-19-gotland-2022",
      "loadoutId": "default",
      "mountId": "tp-47",
      "weaponId": "cmo-weapon-3936",
      "quantity": 16
    },
    {
      "platformId": "a-19-gotland-2022",
      "loadoutId": "default",
      "mountId": "tp-62",
      "weaponId": "cmo-weapon-901",
      "quantity": 16
    },
    {
      "platformId": "f-16c-blk-52iq-falcon-2015",
      "loadoutId": "default",
      "mountId": "300-usg-drop-tank",
      "weaponId": "cmo-weapon-1523",
      "quantity": 16
    },
    {
      "platformId": "f-16c-blk-52iq-falcon-2015",
      "loadoutId": "default",
      "mountId": "370-usg-drop-tank",
      "weaponId": "cmo-weapon-1763",
      "quantity": 16
    },
    {
      "platformId": "f-16c-blk-52iq-falcon-2015",
      "loadoutId": "default",
      "mountId": "agm-65k-maverick-ir",
      "weaponId": "cmo-weapon-22",
      "quantity": 16
    },
    {
      "platformId": "f-16c-blk-52iq-falcon-2015",
      "loadoutId": "default",
      "mountId": "aim",
      "weaponId": "cmo-weapon-1384",
      "quantity": 16
    },
    {
      "platformId": "f-16c-blk-52iq-falcon-2015",
      "loadoutId": "default",
      "mountId": "aim-7m-sparrow-iii",
      "weaponId": "cmo-weapon-1400",
      "quantity": 16
    },
    {
      "platformId": "f-16c-blk-52iq-falcon-2015",
      "loadoutId": "default",
      "mountId": "aim-9m-sidewinder",
      "weaponId": "cmo-weapon-1384",
      "quantity": 16
    },
    {
      "platformId": "f-16c-blk-52iq-falcon-2015",
      "loadoutId": "default",
      "mountId": "an-aaq",
      "weaponId": "cmo-weapon-459",
      "quantity": 16
    },
    {
      "platformId": "f-16c-blk-52iq-falcon-2015",
      "loadoutId": "default",
      "mountId": "an-aaq-33-sniper-xr-pod-flir-lrmts-40k-ft",
      "weaponId": "cmo-weapon-459",
      "quantity": 16
    },
    {
      "platformId": "f-16c-blk-52iq-falcon-2015",
      "loadoutId": "default",
      "mountId": "gbu-10e-b-paveway-ii-lgb-mk84",
      "weaponId": "cmo-weapon-1920",
      "quantity": 16
    },
    {
      "platformId": "f-16c-blk-52iq-falcon-2015",
      "loadoutId": "default",
      "mountId": "gbu-12d-b-paveway-ii-lgb-mk82",
      "weaponId": "cmo-weapon-1906",
      "quantity": 16
    },
    {
      "platformId": "f-16c-blk-52iq-falcon-2015",
      "loadoutId": "default",
      "mountId": "gbu-24a-b-paveway-iii-lgb-blu-109-b",
      "weaponId": "cmo-weapon-871",
      "quantity": 16
    },
    {
      "platformId": "f-16c-blk-52iq-falcon-2015",
      "loadoutId": "default",
      "mountId": "mk82-500lb-ldgp",
      "weaponId": "cmo-weapon-1814",
      "quantity": 16
    },
    {
      "platformId": "f-16c-blk-52iq-falcon-2015",
      "loadoutId": "default",
      "mountId": "mk84-2000lb-ldgp",
      "weaponId": "cmo-weapon-1839",
      "quantity": 16
    },
    {
      "platformId": "f-219-sachsen-type-f124-2006",
      "loadoutId": "default",
      "mountId": "27mm-mlg-27-burst-20-rnds",
      "weaponId": "cmo-weapon-680",
      "quantity": 200
    },
    {
      "platformId": "f-219-sachsen-type-f124-2006",
      "loadoutId": "default",
      "mountId": "76mm-62-super-rapido-he-burst-2-rnds",
      "weaponId": "cmo-weapon-166",
      "quantity": 200
    },
    {
      "platformId": "f-219-sachsen-type-f124-2006",
      "loadoutId": "default",
      "mountId": "an-slq-25-nixie",
      "weaponId": "cmo-weapon-1068",
      "quantity": 16
    },
    {
      "platformId": "f-219-sachsen-type-f124-2006",
      "loadoutId": "default",
      "mountId": "bullfighter-chaff-flare-seduction",
      "weaponId": "cmo-weapon-1273",
      "quantity": 16
    },
    {
      "platformId": "f-219-sachsen-type-f124-2006",
      "loadoutId": "default",
      "mountId": "mu-90-impact",
      "weaponId": "cmo-weapon-1450",
      "quantity": 16
    },
    {
      "platformId": "f-219-sachsen-type-f124-2006",
      "loadoutId": "default",
      "mountId": "rgm-84d-harpoon-ic",
      "weaponId": "cmo-weapon-1611",
      "quantity": 16
    },
    {
      "platformId": "f-219-sachsen-type-f124-2006",
      "loadoutId": "default",
      "mountId": "rim-116b-ram-blk-i",
      "weaponId": "cmo-weapon-1000",
      "quantity": 16
    },
    {
      "platformId": "f-219-sachsen-type-f124-2006",
      "loadoutId": "default",
      "mountId": "rim-162b-essm",
      "weaponId": "cmo-weapon-927",
      "quantity": 16
    },
    {
      "platformId": "f-219-sachsen-type-f124-2006",
      "loadoutId": "default",
      "mountId": "rim-66m-2-sm-2mr-blk-iiia",
      "weaponId": "cmo-weapon-1195",
      "quantity": 16
    },
    {
      "platformId": "f-341-absalon-2020",
      "loadoutId": "default",
      "mountId": "12-7mm-50-mg-burst-10-rnds",
      "weaponId": "cmo-weapon-1695",
      "quantity": 200
    },
    {
      "platformId": "f-341-absalon-2020",
      "loadoutId": "default",
      "mountId": "127mm-62-he-cvt-hifrag",
      "weaponId": "cmo-weapon-1394",
      "quantity": 200
    },
    {
      "platformId": "f-341-absalon-2020",
      "loadoutId": "default",
      "mountId": "127mm-62-he-pd-hicap",
      "weaponId": "cmo-weapon-596",
      "quantity": 200
    },
    {
      "platformId": "f-341-absalon-2020",
      "loadoutId": "default",
      "mountId": "127mm-62-wp",
      "weaponId": "cmo-weapon-597",
      "quantity": 200
    },
    {
      "platformId": "f-341-absalon-2020",
      "loadoutId": "default",
      "mountId": "35mm-79-oerlikon-millennium-gdm-008-ahead-burst-24-rnds",
      "weaponId": "cmo-weapon-2023",
      "quantity": 200
    },
    {
      "platformId": "f-341-absalon-2020",
      "loadoutId": "default",
      "mountId": "chimera-chaff-flare-seduction-round",
      "weaponId": "cmo-weapon-1274",
      "quantity": 16
    },
    {
      "platformId": "f-341-absalon-2020",
      "loadoutId": "default",
      "mountId": "fim-92e-stinger-rmp-blk-i",
      "weaponId": "cmo-weapon-496",
      "quantity": 16
    },
    {
      "platformId": "f-341-absalon-2020",
      "loadoutId": "default",
      "mountId": "mu-90-impact",
      "weaponId": "cmo-weapon-1450",
      "quantity": 16
    },
    {
      "platformId": "f-341-absalon-2020",
      "loadoutId": "default",
      "mountId": "rgm-84l-harpoon-ii",
      "weaponId": "cmo-weapon-589",
      "quantity": 16
    },
    {
      "platformId": "f-341-absalon-2020",
      "loadoutId": "default",
      "mountId": "rim-162c-essm",
      "weaponId": "cmo-weapon-926",
      "quantity": 16
    },
    {
      "platformId": "jas-39a-gripen-1997",
      "loadoutId": "default",
      "mountId": "1200-liter-drop-tank",
      "weaponId": "cmo-weapon-1536",
      "quantity": 16
    },
    {
      "platformId": "jas-39a-gripen-1997",
      "loadoutId": "default",
      "mountId": "1275-liter-drop-tank",
      "weaponId": "cmo-weapon-21",
      "quantity": 16
    },
    {
      "platformId": "jas-39a-gripen-1997",
      "loadoutId": "default",
      "mountId": "bk-90-mjolner-mk1-72-x-mj1-anti-personnel",
      "weaponId": "cmo-weapon-1072",
      "quantity": 16
    },
    {
      "platformId": "jas-39a-gripen-1997",
      "loadoutId": "default",
      "mountId": "bk-90-mjolner-mk2-24-x-mj2-anti-tank",
      "weaponId": "cmo-weapon-1071",
      "quantity": 16
    },
    {
      "platformId": "jas-39a-gripen-1997",
      "loadoutId": "default",
      "mountId": "m-70-135mm-rocket",
      "weaponId": "cmo-weapon-1019",
      "quantity": 16
    },
    {
      "platformId": "jas-39a-gripen-1997",
      "loadoutId": "default",
      "mountId": "rb-15f-mk1",
      "weaponId": "cmo-weapon-290",
      "quantity": 16
    },
    {
      "platformId": "jas-39a-gripen-1997",
      "loadoutId": "default",
      "mountId": "rb-74-sidewinder-aim-9l",
      "weaponId": "cmo-weapon-1021",
      "quantity": 16
    },
    {
      "platformId": "jas-39a-gripen-1997",
      "loadoutId": "default",
      "mountId": "rb-75-maverick-eo-agm-65b",
      "weaponId": "cmo-weapon-1020",
      "quantity": 16
    },
    {
      "platformId": "jas-39b-gripen-1997",
      "loadoutId": "default",
      "mountId": "1200-liter-drop-tank",
      "weaponId": "cmo-weapon-1536",
      "quantity": 16
    },
    {
      "platformId": "jas-39b-gripen-1997",
      "loadoutId": "default",
      "mountId": "1275-liter-drop-tank",
      "weaponId": "cmo-weapon-21",
      "quantity": 16
    },
    {
      "platformId": "jas-39b-gripen-1997",
      "loadoutId": "default",
      "mountId": "bk-90-mjolner-mk1-72-x-mj1-anti-personnel",
      "weaponId": "cmo-weapon-1072",
      "quantity": 16
    },
    {
      "platformId": "jas-39b-gripen-1997",
      "loadoutId": "default",
      "mountId": "bk-90-mjolner-mk2-24-x-mj2-anti-tank",
      "weaponId": "cmo-weapon-1071",
      "quantity": 16
    },
    {
      "platformId": "jas-39b-gripen-1997",
      "loadoutId": "default",
      "mountId": "m-70-135mm-rocket",
      "weaponId": "cmo-weapon-1019",
      "quantity": 16
    },
    {
      "platformId": "jas-39b-gripen-1997",
      "loadoutId": "default",
      "mountId": "rb-15f-mk1",
      "weaponId": "cmo-weapon-290",
      "quantity": 16
    },
    {
      "platformId": "jas-39b-gripen-1997",
      "loadoutId": "default",
      "mountId": "rb-74-sidewinder-aim-9l",
      "weaponId": "cmo-weapon-1021",
      "quantity": 16
    },
    {
      "platformId": "jas-39b-gripen-1997",
      "loadoutId": "default",
      "mountId": "rb-75-maverick-eo-agm-65b",
      "weaponId": "cmo-weapon-1020",
      "quantity": 16
    },
    {
      "platformId": "jas-39c-gripen-2005",
      "loadoutId": "default",
      "mountId": "1275-liter-drop-tank",
      "weaponId": "cmo-weapon-21",
      "quantity": 16
    },
    {
      "platformId": "jas-39c-gripen-2005",
      "loadoutId": "default",
      "mountId": "aim",
      "weaponId": "cmo-weapon-1384",
      "quantity": 16
    },
    {
      "platformId": "jas-39c-gripen-2005",
      "loadoutId": "default",
      "mountId": "aim-9l-sidewinder",
      "weaponId": "cmo-weapon-1401",
      "quantity": 16
    },
    {
      "platformId": "jas-39e-gripen-ng-2021",
      "loadoutId": "default",
      "mountId": "1200-liter-drop-tank",
      "weaponId": "cmo-weapon-1536",
      "quantity": 16
    },
    {
      "platformId": "jas-39e-gripen-ng-2021",
      "loadoutId": "default",
      "mountId": "1275-liter-drop-tank",
      "weaponId": "cmo-weapon-21",
      "quantity": 16
    },
    {
      "platformId": "jas-39e-gripen-ng-2021",
      "loadoutId": "default",
      "mountId": "bk-90-mjolner-mk1-72-x-mj1-anti-personnel",
      "weaponId": "cmo-weapon-1072",
      "quantity": 16
    },
    {
      "platformId": "jas-39e-gripen-ng-2021",
      "loadoutId": "default",
      "mountId": "bk-90-mjolner-mk2-24-x-mj2-anti-tank",
      "weaponId": "cmo-weapon-1071",
      "quantity": 16
    },
    {
      "platformId": "jas-39e-gripen-ng-2021",
      "loadoutId": "default",
      "mountId": "gbu-12d-b-paveway-ii-lgb-mk82",
      "weaponId": "cmo-weapon-1906",
      "quantity": 16
    },
    {
      "platformId": "jas-39e-gripen-ng-2021",
      "loadoutId": "default",
      "mountId": "litening-iii-pod-flir-lrmts-40k-ft",
      "weaponId": "cmo-weapon-1292",
      "quantity": 16
    },
    {
      "platformId": "jas-39e-gripen-ng-2021",
      "loadoutId": "default",
      "mountId": "m-70-135mm-rocket",
      "weaponId": "cmo-weapon-1019",
      "quantity": 16
    },
    {
      "platformId": "jas-39e-gripen-ng-2021",
      "loadoutId": "default",
      "mountId": "rb-101-meteor",
      "weaponId": "cmo-weapon-371",
      "quantity": 16
    },
    {
      "platformId": "jas-39e-gripen-ng-2021",
      "loadoutId": "default",
      "mountId": "rb-15f-mk2",
      "weaponId": "cmo-weapon-282",
      "quantity": 16
    },
    {
      "platformId": "jas-39e-gripen-ng-2021",
      "loadoutId": "default",
      "mountId": "rb-75-maverick-eo-agm-65b",
      "weaponId": "cmo-weapon-1020",
      "quantity": 16
    },
    {
      "platformId": "jas-39e-gripen-ng-2021",
      "loadoutId": "default",
      "mountId": "rb-98-aim",
      "weaponId": "cmo-weapon-1128",
      "quantity": 16
    },
    {
      "platformId": "jas-39e-gripen-ng-2021",
      "loadoutId": "default",
      "mountId": "rb-98-aim-2000a-iris-t",
      "weaponId": "cmo-weapon-1128",
      "quantity": 16
    },
    {
      "platformId": "jas-39e-gripen-ng-2021",
      "loadoutId": "default",
      "mountId": "spk-39-pod-eo",
      "weaponId": "cmo-weapon-1291",
      "quantity": 16
    },
    {
      "platformId": "k-31-visby-2009",
      "loadoutId": "default",
      "mountId": "57mm-70-bofors-mk3-gp-burst-4-rnds",
      "weaponId": "cmo-weapon-1140",
      "quantity": 200
    },
    {
      "platformId": "k-31-visby-2009",
      "loadoutId": "default",
      "mountId": "dual-trap-chaff-flare",
      "weaponId": "cmo-weapon-455",
      "quantity": 16
    },
    {
      "platformId": "mpk-steregushchiy-pr-20380-2018",
      "loadoutId": "default",
      "mountId": "100mm-59-a-190-frag",
      "weaponId": "cmo-weapon-495",
      "quantity": 200
    },
    {
      "platformId": "mpk-steregushchiy-pr-20380-2018",
      "loadoutId": "default",
      "mountId": "100mm-59-a-190-he",
      "weaponId": "cmo-weapon-494",
      "quantity": 200
    },
    {
      "platformId": "mpk-steregushchiy-pr-20380-2018",
      "loadoutId": "default",
      "mountId": "14-5mm-mg-burst-20-rnds",
      "weaponId": "cmo-weapon-1110",
      "quantity": 200
    },
    {
      "platformId": "mpk-steregushchiy-pr-20380-2018",
      "loadoutId": "default",
      "mountId": "30mm-twin-gatling-gsh-6-30kd-375-rnds",
      "weaponId": "cmo-weapon-2183",
      "quantity": 200
    },
    {
      "platformId": "mpk-steregushchiy-pr-20380-2018",
      "loadoutId": "default",
      "mountId": "ak",
      "weaponId": "cmo-weapon-1374",
      "quantity": 200
    },
    {
      "platformId": "mpk-steregushchiy-pr-20380-2018",
      "loadoutId": "default",
      "mountId": "ak-630m-30mm-65-gatling-burst-400-rnds",
      "weaponId": "cmo-weapon-1108",
      "quantity": 200
    },
    {
      "platformId": "mpk-steregushchiy-pr-20380-2018",
      "loadoutId": "default",
      "mountId": "paket-nk-m-15-anti-torpedo-torpedo",
      "weaponId": "cmo-weapon-3153",
      "quantity": 16
    },
    {
      "platformId": "mpk-steregushchiy-pr-20380-2018",
      "loadoutId": "default",
      "mountId": "paket-nk-mtt-asw",
      "weaponId": "cmo-weapon-2694",
      "quantity": 16
    },
    {
      "platformId": "mpk-steregushchiy-pr-20380-2018",
      "loadoutId": "default",
      "mountId": "pk-10-chaff-sr-50",
      "weaponId": "cmo-weapon-1228",
      "quantity": 16
    },
    {
      "platformId": "mpk-steregushchiy-pr-20380-2018",
      "loadoutId": "default",
      "mountId": "pk-10-flare-so-50",
      "weaponId": "cmo-weapon-1227",
      "quantity": 16
    },
    {
      "platformId": "mpk-steregushchiy-pr-20380-2018",
      "loadoutId": "default",
      "mountId": "sa-n-11b-grisom-9m311k-1",
      "weaponId": "cmo-weapon-2182",
      "quantity": 16
    },
    {
      "platformId": "mpk-steregushchiy-pr-20380-2018",
      "loadoutId": "default",
      "mountId": "ss-n-25-switchblade-kh-35-uran-glonass",
      "weaponId": "cmo-weapon-969",
      "quantity": 16
    },
    {
      "platformId": "mrk-buyan-mod-pr-21631-buyan-m-2014",
      "loadoutId": "default",
      "mountId": "100mm-59-a-190-frag",
      "weaponId": "cmo-weapon-495",
      "quantity": 200
    },
    {
      "platformId": "mrk-buyan-mod-pr-21631-buyan-m-2014",
      "loadoutId": "default",
      "mountId": "100mm-59-a-190-he",
      "weaponId": "cmo-weapon-494",
      "quantity": 200
    },
    {
      "platformId": "mrk-buyan-mod-pr-21631-buyan-m-2014",
      "loadoutId": "default",
      "mountId": "14-5mm-mg-burst-20-rnds",
      "weaponId": "cmo-weapon-1110",
      "quantity": 200
    },
    {
      "platformId": "mrk-buyan-mod-pr-21631-buyan-m-2014",
      "loadoutId": "default",
      "mountId": "ak",
      "weaponId": "cmo-weapon-1374",
      "quantity": 200
    },
    {
      "platformId": "mrk-buyan-mod-pr-21631-buyan-m-2014",
      "loadoutId": "default",
      "mountId": "ak-630m-30mm-65-twin-gatling-burst-800-rnds",
      "weaponId": "cmo-weapon-3038",
      "quantity": 200
    },
    {
      "platformId": "mrk-buyan-mod-pr-21631-buyan-m-2014",
      "loadoutId": "default",
      "mountId": "pk-10-chaff-sr-50",
      "weaponId": "cmo-weapon-1228",
      "quantity": 16
    },
    {
      "platformId": "mrk-buyan-mod-pr-21631-buyan-m-2014",
      "loadoutId": "default",
      "mountId": "pk-10-flare-so-50",
      "weaponId": "cmo-weapon-1227",
      "quantity": 16
    },
    {
      "platformId": "mrk-buyan-mod-pr-21631-buyan-m-2014",
      "loadoutId": "default",
      "mountId": "sa-n-24-grinch-9m342",
      "weaponId": "cmo-weapon-2693",
      "quantity": 16
    },
    {
      "platformId": "mrk-buyan-mod-pr-21631-buyan-m-2014",
      "loadoutId": "default",
      "mountId": "ss-n-27-sizzler-3m54t-kalibr",
      "weaponId": "cmo-weapon-3218",
      "quantity": 16
    },
    {
      "platformId": "mrk-buyan-mod-pr-21631-buyan-m-2014",
      "loadoutId": "default",
      "mountId": "ss-n-30a-sagaris-3m14-kalibr",
      "weaponId": "cmo-weapon-2713",
      "quantity": 16
    }
  ],
  "emcon": [],
  "source": "assets/data/catalog/baltic_patrol.db"
}
