{
  "version": 1,
  "description": "Gauntlet hindsight defect registry — closed defects are re-run by tools/qa-gauntlet/retest-defect.sh",
  "defects": [
    {
      "id": "GAUNTLET-MD-001",
      "status": "closed",
      "class": "sim-code",
      "title": "Air/sub multi-domain shooters must launch (not detection-only)",
      "scenarioId": "gauntlet-multidomain-shooters",
      "seed": 42,
      "ticks": 10,
      "policyPath": "data/scenarios/gauntlet-multidomain-shooters.policy.json",
      "priorFailureMode": "hostile-1",
      "fixSummary": "Multi-agent blue assignment + PreferredHostileByShooter for concurrent domain engages",
      "closedUtc": "2026-07-13T22:00:00Z"
    },
    {
      "id": "GAUNTLET-SYN-T12-001",
      "status": "closed",
      "class": "scenario-data",
      "title": "Tiers 1–2 synthetic u1/hostile combat path",
      "scenarioId": "gauntlet-t1-patrol-b",
      "seed": 42,
      "ticks": 6,
      "policyPath": "data/scenarios/gauntlet-t1-patrol-b.policy.json",
      "priorFailureMode": "CATALOG_UNIT:u1:",
      "fixSummary": "Catalog Visby/Sovremenny units + side registry",
      "closedUtc": "2026-07-13T20:00:00Z"
    }
  ]
}
